ai_migrate/__init__.py
ai_migrate/aggregate_manifests.py
ai_migrate/cli.py
ai_migrate/eval_generator.py
ai_migrate/examples.py
ai_migrate/fake_llm_client.py
ai_migrate/git.py
ai_migrate/git_identity.py
ai_migrate/manifest.py
ai_migrate/merge_migrator_changes.py
ai_migrate/migrate.py
ai_migrate/pr_utils.py
ai_migrate/progress.py
ai_migrate/projects.py
ai_migrate/projects_root.py
ai_migrate/resolve_symbols.py
ai_migrate/run_eval.py
ai_migrate/test_eval_generator.py
ai_migrate/test_manifest.py
ai_migrate/test_migrate.py
ai_migrate/test_resolve_symbols.py
ai_migrate/llm_providers/__init__.py
ai_migrate/llm_providers/base.py
ai_migrate/llm_providers/openai.py
ai_migrate/test/eval_test_data/response1.txt
ai_migrate/test/examples/single.new.py
ai_migrate/test/examples/single.old.py
ai_migrate/test/examples/example1.new/src/file1.py
ai_migrate/test/examples/example1.new/src/file2.py
ai_migrate/test/examples/example1.old/src/file1.py
ai_migrate/test/examples/example1.old/src/file2.py
ai_migrate_tools-0.1.3.dist-info/METADATA
ai_migrate_tools-0.1.3.dist-info/WHEEL
ai_migrate_tools-0.1.3.dist-info/entry_points.txt
ai_migrate_tools-0.1.3.dist-info/licenses/LICENSE
ai_migrate_tools-0.1.3.dist-info/RECORD
