Metadata-Version: 2.4
Name: ai-migrate-tools
Version: 0.1.3
Summary: LLM-powered code migrations at scale
License-Expression: Apache-2.0
License-File: LICENSE
Requires-Python: >=3.13
Requires-Dist: click>=8.1.0
Requires-Dist: httpx>=0.24.0
Requires-Dist: openai>=1.0.0
Requires-Dist: prompt-toolkit>=3.0.0
Requires-Dist: pytest
Requires-Dist: pytest-asyncio
Requires-Dist: rich>=13.0.0
Requires-Dist: tiktoken>=0.9.0
